{"lexeme_id": 1, "entry_id": 1, "human_id": "tēls:1", "paradigm_name": "noun-1a-phono", "lemma": "t ææ l s"}
{"lexeme_id": 2, "entry_id": 2, "human_id": "mērs:1", "paradigm_name": "noun-1a-phono", "lemma": "m ee r s"}
{"lexeme_id": 3, "entry_id": 3, "human_id": "ēst:1", "paradigm_name": "verb-1-phono", "lemma": "ee s t"}
{"lexeme_id": 4, "entry_id": 4, "human_id": "džouls:1", "paradigm_name": "noun-1a-phono", "lemma": "dž ɔu l s"}
{"lexeme_id": 5, "entry_id": 5, "human_id": "pelt:1", "paradigm_name": "verb-1-phono", "lemma": "p e l t"}
{"lexeme_id": 6, "entry_id": 6, "human_id": "kaps:1", "paradigm_name": "noun-1a-phono", "lemma": "k a p s"}
{"lexeme_id": 7, "entry_id": 7, "human_id": "zāle:1", "paradigm_name": "noun-5fa-phono", "lemma": "z aa= l ex"}
{"lexeme_id": 8, "entry_id": 8, "human_id": "zāle:2", "paradigm_name": "noun-5fa-phono", "lemma": "z aaq l ex"}